README.md
setup.py
deetlist/__init__.py
deetlist/settings.py
deetlist.egg-info/PKG-INFO
deetlist.egg-info/SOURCES.txt
deetlist.egg-info/dependency_links.txt
deetlist.egg-info/top_level.txt
deetlist/crawler/__init__.py
deetlist/fetcher/__init__.py
deetlist/fetcher/base.py
deetlist/fetcher/dragons/__init__.py
deetlist/fetcher/dragons/all.py
deetlist/fetcher/dragons/new.py
deetlist/fetcher/dragons/page.py
deetlist/fetcher/islands/__init__.py
deetlist/fetcher/islands/fog_islands.py
deetlist/fetcher/islands/grid_islands.py
deetlist/fetcher/islands/heroic_races.py
deetlist/fetcher/islands/maze_islands.py
deetlist/fetcher/islands/puzzle_islands.py
deetlist/fetcher/islands/runner_islands.py
deetlist/fetcher/islands/tower_islands.py
deetlist/parser/__init__.py
deetlist/parser/dragons/__init__.py
deetlist/parser/dragons/all.py
deetlist/parser/dragons/new.py
deetlist/parser/dragons/page.py
deetlist/parser/islands/__init__.py
deetlist/parser/islands/fog_islands.py
deetlist/parser/islands/grid_islands.py
deetlist/parser/islands/tower_islands.py
deetlist/parser/islands/heroic_races/__init__.py
deetlist/parser/islands/heroic_races/lap.py
deetlist/parser/islands/heroic_races/mission.py
deetlist/parser/islands/heroic_races/node.py
deetlist/parser/islands/maze_islands/__init__.py
deetlist/parser/islands/maze_islands/dragon.py
deetlist/parser/islands/maze_islands/node.py
deetlist/parser/islands/maze_islands/path.py
deetlist/parser/islands/puzzle_islands/__init__.py
deetlist/parser/islands/puzzle_islands/mission.py
deetlist/parser/islands/runner_islands/__init__.py
deetlist/parser/islands/runner_islands/mission.py
deetlist/parser/islands/runner_islands/mission_set.py
deetlist/scraper/__init__.py
deetlist/scraper/base.py
deetlist/scraper/dragons/__init__.py
deetlist/scraper/dragons/all.py
deetlist/scraper/dragons/new.py
deetlist/scraper/dragons/page.py
deetlist/scraper/islands/__init__.py
deetlist/scraper/islands/fog_islands.py
deetlist/scraper/islands/grid_islands.py
deetlist/scraper/islands/heroic_races.py
deetlist/scraper/islands/maze_islands.py
deetlist/scraper/islands/puzzle_islands.py
